apathetic_utils/__init__.py
apathetic_utils/ci.py
apathetic_utils/constants.py
apathetic_utils/files.py
apathetic_utils/matching.py
apathetic_utils/modules.py
apathetic_utils/namespace.py
apathetic_utils/paths.py
apathetic_utils/py.typed
apathetic_utils/runtime.py
apathetic_utils/subprocess_utils.py
apathetic_utils/testing.py
apathetic_utils/text.py
apathetic_utils/types.py
apathetic_utils/version.py
apathetic_utils-0.5.2.dist-info/METADATA
apathetic_utils-0.5.2.dist-info/WHEEL
apathetic_utils-0.5.2.dist-info/entry_points.txt
apathetic_utils-0.5.2.dist-info/licenses/LICENSE
apathetic_utils-0.5.2.dist-info/RECORD
