Metadata-Version: 2.4
Name: apathetic-utils
Version: 0.5.2
Summary: When stdlib is almost enough.
License-File: LICENSE
Keywords: library,utilities,utils
Author: Apathetic Tools
Requires-Python: >=3.10
Classifier: Development Status :: 3 - Alpha
Classifier: Intended Audience :: Developers
Classifier: Operating System :: OS Independent
Classifier: Programming Language :: Python :: 3
Classifier: Programming Language :: Python :: 3 :: Only
Classifier: Programming Language :: Python :: 3.10
Classifier: Programming Language :: Python :: 3.11
Classifier: Programming Language :: Python :: 3.12
Classifier: Topic :: Software Development :: Libraries :: Python Modules
Classifier: Topic :: Utilities
Requires-Dist: apathetic-logging (>=0.3.2,<2.0.0)
Project-URL: Changelog, https://github.com/apathetic-tools/python-utils/releases
Project-URL: Documentation, https://apathetic-tools.github.io/python-utils/
Project-URL: Homepage, https://github.com/apathetic-tools/python-utils
Project-URL: Issues, https://github.com/apathetic-tools/python-utils/issues
Project-URL: Repository, https://github.com/apathetic-tools/python-utils
